pychan/__init__.py
pychan/__main__.py
pychan/api.py
pychan/logger.py
pychan/models.py
pychan/py.typed
pychan-0.9.0.dist-info/LICENSE
pychan-0.9.0.dist-info/METADATA
pychan-0.9.0.dist-info/WHEEL
pychan-0.9.0.dist-info/top_level.txt
pychan-0.9.0.dist-info/RECORD
