Metadata-Version: 2.1
Name: pychan
Version: 0.9.0
Summary: A Python library for interacting with 4chan in a programmatically-friendly way.
Home-page: https://github.com/cooperwalbrun/pychan
Author: cooperwalbrun
Author-email: mail@cooperwalbrun.io
Platform: any
Classifier: Programming Language :: Python :: 3.10
Classifier: Programming Language :: Python :: 3.11
Classifier: Programming Language :: Python :: 3.12
Classifier: License :: OSI Approved :: GNU General Public License v3 (GPLv3)
Classifier: Operating System :: OS Independent
Requires-Python: <4,>=3.10
License-File: LICENSE
Requires-Dist: beautifulsoup4 <5,>=4.11.1
Requires-Dist: importlib-metadata
Requires-Dist: pyrate-limiter <4,>=3
Requires-Dist: requests <3,>=2.28
Requires-Dist: types-beautifulsoup4 <5,>=4.11
Requires-Dist: types-requests <3,>=2.28
Provides-Extra: development
Requires-Dist: mypy ; extra == 'development'
Requires-Dist: pytest ; extra == 'development'
Requires-Dist: pytest-cov ; extra == 'development'
Requires-Dist: pytest-mock ; extra == 'development'
Requires-Dist: responses ; extra == 'development'
Requires-Dist: tox ; extra == 'development'
Requires-Dist: yapf ; extra == 'development'
Provides-Extra: github_actions
Requires-Dist: mypy ; extra == 'github_actions'
Requires-Dist: pytest ; extra == 'github_actions'
Requires-Dist: pytest-cov ; extra == 'github_actions'
Requires-Dist: pytest-mock ; extra == 'github_actions'
Requires-Dist: responses ; extra == 'github_actions'
Requires-Dist: tox ; extra == 'github_actions'
Requires-Dist: tox-gh-actions ; extra == 'github_actions'
Provides-Extra: testing
Requires-Dist: mypy ; extra == 'testing'
Requires-Dist: pytest ; extra == 'testing'
Requires-Dist: pytest-cov ; extra == 'testing'
Requires-Dist: pytest-mock ; extra == 'testing'
Requires-Dist: responses ; extra == 'testing'
Requires-Dist: tox ; extra == 'testing'
